{
  "event_count": 94,
  "last_event_id": "01KTKJ0TWA9B68X69GGW5ZWCFT",
  "materialized_at": "2026-06-08T12:06:20.298454+00:00",
  "mission_number": "",
  "mission_slug": "execution-state-canonical-surface-01KTG6P9",
  "mission_type": "software-dev",
  "summary": {
    "approved": 14,
    "blocked": 0,
    "canceled": 0,
    "claimed": 0,
    "done": 0,
    "for_review": 0,
    "in_progress": 0,
    "in_review": 0,
    "planned": 0
  },
  "work_packages": {
    "WP01": {
      "actor": "user",
      "force_count": 0,
      "lane": "approved",
      "last_event_id": "01KTJSDKPSKPV7JJD9CMFZX0JX",
      "last_transition_at": "2026-06-08T04:56:24.537526+00:00"
    },
    "WP02": {
      "actor": "user",
      "force_count": 0,
      "lane": "approved",
      "last_event_id": "01KTJRX9QZFHB55S4EB2F0XAT8",
      "last_transition_at": "2026-06-08T04:47:30.048041+00:00"
    },
    "WP03": {
      "actor": "user",
      "force_count": 0,
      "lane": "approved",
      "last_event_id": "01KTJTGH50QSZCQDHZC1STV9GB",
      "last_transition_at": "2026-06-08T05:15:28.800910+00:00"
    },
    "WP04": {
      "actor": "user",
      "force_count": 0,
      "lane": "approved",
      "last_event_id": "01KTK4T518AXQEFW6H5DYWGJRR",
      "last_transition_at": "2026-06-08T08:15:29.832783+00:00"
    },
    "WP05": {
      "actor": "user",
      "force_count": 0,
      "lane": "approved",
      "last_event_id": "01KTK5XASYTMF9CHJ0XNWETT9T",
      "last_transition_at": "2026-06-08T08:34:42.622282+00:00"
    },
    "WP06": {
      "actor": "user",
      "force_count": 0,
      "lane": "approved",
      "last_event_id": "01KTK7MFGEFJQ9VTX6NKYED79F",
      "last_transition_at": "2026-06-08T09:04:49.678725+00:00"
    },
    "WP07": {
      "actor": "user",
      "force_count": 1,
      "lane": "approved",
      "last_event_id": "01KTK8KRDH8VF08MMNKD35AZNG",
      "last_transition_at": "2026-06-08T09:21:54.609425+00:00"
    },
    "WP08": {
      "actor": "user",
      "force_count": 0,
      "lane": "approved",
      "last_event_id": "01KTK9Q0EGX9ZC8F98VG3P2S29",
      "last_transition_at": "2026-06-08T09:41:09.712079+00:00"
    },
    "WP09": {
      "actor": "user",
      "force_count": 0,
      "lane": "approved",
      "last_event_id": "01KTKABZHQZW30SCN6NCCJZJF0",
      "last_transition_at": "2026-06-08T09:52:36.919289+00:00"
    },
    "WP10": {
      "actor": "user",
      "force_count": 0,
      "lane": "approved",
      "last_event_id": "01KTKCDD4YYRK98H6MJJN03MH3",
      "last_transition_at": "2026-06-08T10:28:20.766388+00:00"
    },
    "WP11": {
      "actor": "user",
      "force_count": 0,
      "lane": "approved",
      "last_event_id": "01KTKD6W9GKB51ZQJ848NSHPMB",
      "last_transition_at": "2026-06-08T10:42:15.472442+00:00"
    },
    "WP12": {
      "actor": "user",
      "force_count": 0,
      "lane": "approved",
      "last_event_id": "01KTKE6GJZ5MERX00AWMZ5P3MG",
      "last_transition_at": "2026-06-08T10:59:32.063144+00:00"
    },
    "WP13": {
      "actor": "user",
      "force_count": 0,
      "lane": "approved",
      "last_event_id": "01KTKFE48V1WGT3NFA31KFZWRB",
      "last_transition_at": "2026-06-08T11:21:10.171444+00:00"
    },
    "WP14": {
      "actor": "user",
      "force_count": 1,
      "lane": "approved",
      "last_event_id": "01KTKJ0TWA9B68X69GGW5ZWCFT",
      "last_transition_at": "2026-06-08T12:06:20.298454+00:00"
    }
  }
}
